pybuilder_aws_plugin
