Metadata-Version: 1.1
Name: pybuilder-aws-plugin
Version: 157
Summary: PyBuilder plugin to handle AWS functionality
Home-page: https://github.com/ImmobilienScout24/pybuilder_aws_plugin
Author: Valentin Haenel, Stefan Neben
Author-email: valentin@haenel.co, stefan.neben@gmail.com
License: Apache
Platform: UNKNOWN
Classifier: Development Status :: 2 - Pre-Alpha
Classifier: Environment :: Console
Classifier: Intended Audience :: Developers
Classifier: Intended Audience :: System Administrators
Classifier: License :: OSI Approved :: Apache Software License
Classifier: Programming Language :: Python
Classifier: Operating System :: POSIX :: Linux
Classifier: Topic :: System :: Software Distribution
Classifier: Topic :: System :: Systems Administration
Classifier: Topic :: System :: Archiving :: Packaging
Classifier: Topic :: Utilities
